relic/core/__init__.py
relic/core/cli.py
relic/core/entrytools.py
relic/core/errors.py
relic/core/lazyio.py
relic/core/logmsg.py
relic/core/py.typed
relic/core/serialization.py
relic/core/typeshed.py
relic_tool_core-2.4.0.dist-info/licenses/LICENSE.txt
relic_tool_core-2.4.0.dist-info/METADATA
relic_tool_core-2.4.0.dist-info/WHEEL
relic_tool_core-2.4.0.dist-info/entry_points.txt
relic_tool_core-2.4.0.dist-info/top_level.txt
relic_tool_core-2.4.0.dist-info/RECORD
