Metadata-Version: 2.4
Name: relic-tool-core
Version: 2.4.0
Summary: The core library used by other Relic-Tool packages.
Author: Marcus Kertesz
Project-URL: Bug Tracker, https://github.com/MAK-Relic-Tool/Issues-Tracker/issues
Project-URL: Homepage, https://github.com/MAK-Relic-Tool/Relic-Tool-Core
Classifier: Programming Language :: Python :: 3 :: Only
Classifier: Programming Language :: Python :: 3.9
Classifier: Programming Language :: Python :: 3.10
Classifier: Programming Language :: Python :: 3.11
Classifier: Programming Language :: Python :: 3.12
Classifier: Programming Language :: Python :: 3.13
Classifier: Typing :: Typed
Classifier: License :: OSI Approved :: GNU General Public License v3 (GPLv3)
Requires-Python: >=3.9
License-File: LICENSE.txt
Requires-Dist: typing-extensions; python_version < "3.12"
Requires-Dist: importlib_metadata>=6.5; python_version < "3.12"
Dynamic: license-file
